gitchangelog/__init__.py
gitchangelog/command_cmd_lines.py
gitchangelog/gitchangelog.py
gitchangelog/gitchangelog.rc.reference
gitchangelog/gitchangelog.rc.reference.v2.1.3
gitchangelog/parameters_to_use.py
gitchangelog/__pycache__/command_cmd_lines.cpython-36.pyc
gitchangelog/__pycache__/gitchangelog.cpython-36.pyc
gitchangelog/__pycache__/parameters_to_use.cpython-36.pyc
gitchangelog/modules/__init__.py
gitchangelog/modules/default_methods.py
gitchangelog/modules/example_logic.py
gitchangelog/modules/mobile_logic.py
gitchangelog/modules/vt_logic.py
gitchangelog/modules/__pycache__/__init__.cpython-36.pyc
gitchangelog/modules/__pycache__/default_methods.cpython-36.pyc
gitchangelog/modules/__pycache__/mobile_logic.cpython-36.pyc
gitchangelog/modules/__pycache__/vt_logic.cpython-36.pyc
gitchangelog/templates/mako/ChangeLog.tpl
gitchangelog/templates/mako/octobercms-plugin.tpl
gitchangelog/templates/mako/restructuredtext.tpl
gitchangelog/templates/mustache/markdown.tpl
gitchangelog/templates/mustache/mobile.tpl
gitchangelog/templates/mustache/restructuredtext.tpl
gitchangelog_vt-3.0.9.dist-info/LICENSE
gitchangelog_vt-3.0.9.dist-info/METADATA
gitchangelog_vt-3.0.9.dist-info/WHEEL
gitchangelog_vt-3.0.9.dist-info/entry_points.txt
gitchangelog_vt-3.0.9.dist-info/top_level.txt
gitchangelog_vt-3.0.9.dist-info/RECORD
