Metadata-Version: 2.1
Name: gitchangelog-vt
Version: 3.0.9
Summary: gitchangelog-vt is a custom version of gitchangelog that generates a changelog thanks to git log.
Home-page: http://github.com/vaab/gitchangelog
Author: Valentin LAB
Author-email: valentin.lab@kalysto.org
License: BSD 3-Clause License
Platform: UNKNOWN
Classifier: Programming Language :: Python
Classifier: Environment :: Console
Classifier: Intended Audience :: Developers
Classifier: License :: OSI Approved :: BSD License
Classifier: Topic :: Software Development
Classifier: Development Status :: 5 - Production/Stable
Classifier: Topic :: Software Development :: Version Control
Classifier: Programming Language :: Python :: 2
Classifier: Programming Language :: Python :: 2.7
Classifier: Programming Language :: Python :: 3
Classifier: Programming Language :: Python :: 3.3
Classifier: Programming Language :: Python :: 3.4
Classifier: Programming Language :: Python :: 3.5
Classifier: Programming Language :: Python :: 3.6
Requires-Dist: pystache
Requires-Dist: mako
Requires-Dist: numpy
Requires-Dist: python-dateutil
Provides-Extra: mako
Requires-Dist: mako ; extra == 'mako'
Provides-Extra: mustache
Requires-Dist: pystache ; extra == 'mustache'
Provides-Extra: test
Requires-Dist: nose ; extra == 'test'
Requires-Dist: minimock ; extra == 'test'
Requires-Dist: mako ; extra == 'test'
Requires-Dist: pystache ; extra == 'test'
